odoo/addons/stock_dangerous_goods/README.rst
odoo/addons/stock_dangerous_goods/__init__.py
odoo/addons/stock_dangerous_goods/__manifest__.py
odoo/addons/stock_dangerous_goods/i18n/it.po
odoo/addons/stock_dangerous_goods/i18n/stock_dangerous_goods.pot
odoo/addons/stock_dangerous_goods/models/__init__.py
odoo/addons/stock_dangerous_goods/models/product_product.py
odoo/addons/stock_dangerous_goods/models/stock_move_line.py
odoo/addons/stock_dangerous_goods/models/stock_quant_package.py
odoo/addons/stock_dangerous_goods/readme/CONTRIBUTORS.rst
odoo/addons/stock_dangerous_goods/readme/DESCRIPTION.rst
odoo/addons/stock_dangerous_goods/static/description/icon.png
odoo/addons/stock_dangerous_goods/static/description/index.html
odoo14_addon_stock_dangerous_goods-14.0.1.0.1.dev7.dist-info/METADATA
odoo14_addon_stock_dangerous_goods-14.0.1.0.1.dev7.dist-info/WHEEL
odoo14_addon_stock_dangerous_goods-14.0.1.0.1.dev7.dist-info/top_level.txt
odoo14_addon_stock_dangerous_goods-14.0.1.0.1.dev7.dist-info/RECORD
